cli/__init__.py
cli/main.py
kubewhisper-2.0.0.dist-info/LICENSE
kubewhisper-2.0.0.dist-info/METADATA
kubewhisper-2.0.0.dist-info/WHEEL
kubewhisper-2.0.0.dist-info/entry_points.txt
kubewhisper-2.0.0.dist-info/top_level.txt
kubewhisper-2.0.0.dist-info/RECORD
