Metadata-Version: 2.1
Name: kubewhisper
Version: 2.0.0
Summary: KubeWhisper - Generate kubectl commands from natural language queries
Home-page: https://github.com/petricbranko/kubewhisper
Author: Branko Petric
Author-email: Branko Petric <bane@brankopetric.com>
Project-URL: Homepage, https://github.com/petricbranko/kubewhisper
Project-URL: Issues, https://github.com/petricbranko/kubewhisper/issues
Classifier: Programming Language :: Python :: 3
Classifier: License :: OSI Approved :: MIT License
Classifier: Operating System :: OS Independent
Requires-Python: >=3.9
License-File: LICENSE
Requires-Dist: requests
Requires-Dist: prompt-toolkit
Requires-Dist: rich>=13.0.0
